paipai/__init__.py
paipai/main.py
paipai-0.0.2.dist-info/METADATA
paipai-0.0.2.dist-info/WHEEL
paipai-0.0.2.dist-info/entry_points.txt
paipai-0.0.2.dist-info/top_level.txt
paipai-0.0.2.dist-info/RECORD
