Metadata-Version: 2.1
Name: paipai
Version: 0.0.2
Summary: pip plus
Home-page: https://github.com/yale8848/paipai
Author: yale
Author-email: royal8848@163.com
License: MIT License
Platform: UNKNOWN
Requires-Python: >=3.6
